CHANGES.txt
MANIFEST.in
Makefile
README.txt
bootstrap.py
buildout.cfg
setup.py
zope.conf
src/zcontact/__init__.py
src/zcontact/application.py
src/zcontact/configure.zcml
src/zcontact/contact.py
src/zcontact/contactcontainer.pt
src/zcontact/export.py
src/zcontact/ftesting.zcml
src/zcontact/interfaces.py
src/zcontact/layer.py
src/zcontact/person.py
src/zcontact/security.zcml
src/zcontact/testing.py
src/zcontact/tests.py
src/zcontact/zcontact-configure.zcml
src/zcontact.egg-info/PKG-INFO
src/zcontact.egg-info/SOURCES.txt
src/zcontact.egg-info/dependency_links.txt
src/zcontact.egg-info/entry_points.txt
src/zcontact.egg-info/not-zip-safe
src/zcontact.egg-info/requires.txt
src/zcontact.egg-info/top_level.txt
src/zcontact/app/__init__.py
src/zcontact/app/about.pt
src/zcontact/app/browser.py
src/zcontact/app/configure.zcml
src/zcontact/app/frontpage.pt
src/zcontact/app/ftests.py
src/zcontact/app/help.pt
src/zcontact/app/manage.pt
src/zcontact/browser/__init__.py
src/zcontact/browser/app.py
src/zcontact/browser/configure.zcml
src/zcontact/browser/contact.py
src/zcontact/browser/ftests.py
src/zcontact/browser/person.py
src/zcontact/browser/print.css
src/zcontact/browser/processing.gif
src/zcontact/browser/tests.py
src/zcontact/browser/widget.py
src/zcontact/browser/zcontact.js
src/zcontact/browser/templates/addFieldForm.pt
src/zcontact/browser/templates/addPhoneNumberForm.pt
src/zcontact/browser/templates/app-noscript.pt
src/zcontact/browser/templates/app.pt
src/zcontact/browser/templates/contact.pt
src/zcontact/browser/templates/contacts-noscript.pt
src/zcontact/browser/templates/contacts.pt
src/zcontact/browser/templates/contactselect.pt
src/zcontact/browser/templates/form.pt
src/zcontact/browser/templates/inlineAddress.pt
src/zcontact/browser/templates/inlineFieldItemMacro.pt
src/zcontact/browser/templates/inlinecontact.pt
src/zcontact/browser/templates/inlinefield.pt
src/zcontact/browser/templates/inlinefieldcontainer-noscript.pt
src/zcontact/browser/templates/inlinefieldcontainer.pt
src/zcontact/browser/templates/list_display.pt
src/zcontact/browser/templates/list_input.pt
src/zcontact/browser/templates/login.pt
src/zcontact/browser/templates/login_failed.pt
src/zcontact/browser/templates/loginform.pt
