Metadata-Version: 1.0
Name: zcontact
Version: 0.1.0a11
Summary: An online contact manager built on Zope 3
Home-page: http://launchpad.net/zcontact
Author: Paul Carduner
Author-email: paul@carduner.net
License: GPL 3
Keywords: zcontact zope3
Platform: UNKNOWN
Classifier: Development Status :: 3 - Alpha
Classifier: Environment :: Web Environment
Classifier: Programming Language :: Python
Classifier: Natural Language :: English
Classifier: Operating System :: OS Independent
Classifier: Topic :: Internet :: WWW/HTTP
Classifier: Framework :: Zope3
